{"nodes":[{"id":"config:Config/Mac/BaseMacEngine.ini","type":"config","name":"BaseMacEngine.ini","filePath":"Config/Mac/BaseMacEngine.ini","summary":"配置 配置文件（63 行）— Unreal Engine 引擎或插件的配置定义。","tags":["engine-config","config","未分析"],"complexity":"moderate"},{"id":"config:Config/Mac/BaseMacInput.ini","type":"config","name":"BaseMacInput.ini","filePath":"Config/Mac/BaseMacInput.ini","summary":"配置 配置文件（7 行）— Unreal Engine 引擎或插件的配置定义。","tags":["engine-config","config","未分析"],"complexity":"simple"},{"id":"config:Config/Mac/DataDrivenPlatformInfo.ini","type":"config","name":"DataDrivenPlatformInfo.ini","filePath":"Config/Mac/DataDrivenPlatformInfo.ini","summary":"配置 配置文件（148 行）— Unreal Engine 引擎或插件的配置定义。","tags":["engine-config","config","未分析"],"complexity":"moderate"},{"id":"config:Config/Mac/MacEditorPerProjectUserSettings.ini","type":"config","name":"MacEditorPerProjectUserSettings.ini","filePath":"Config/Mac/MacEditorPerProjectUserSettings.ini","summary":"配置 配置文件（22 行）— Unreal Engine 引擎或插件的配置定义。","tags":["engine-config","config","未分析"],"complexity":"simple"},{"id":"config:Config/Mac/MacGame.ini","type":"config","name":"MacGame.ini","filePath":"Config/Mac/MacGame.ini","summary":"配置 配置文件（1 行）— Unreal Engine 引擎或插件的配置定义。","tags":["engine-config","config","未分析"],"complexity":"simple"},{"id":"config:Config/Mac/Mac_SDK.json","type":"config","name":"Mac_SDK.json","filePath":"Config/Mac/Mac_SDK.json","summary":"JSON 配置文件（12 行）— Unreal Engine 引擎或插件的配置定义。","tags":["engine-config","json","config"],"complexity":"simple"}],"edges":[]}